scrapingfish/__init__.py
scrapingfish/example.py
scrapingfish-0.1.0.dist-info/LICENSE
scrapingfish-0.1.0.dist-info/METADATA
scrapingfish-0.1.0.dist-info/WHEEL
scrapingfish-0.1.0.dist-info/top_level.txt
scrapingfish-0.1.0.dist-info/RECORD
