Metadata-Version: 2.1
Name: scrapingfish
Version: 0.1.0
Project-URL: Homepage, https://github.com/swoutch/scrapingfish
Classifier: Programming Language :: Python :: 3
Classifier: License :: OSI Approved :: MIT License
Classifier: Operating System :: OS Independent
License-File: LICENSE
